gh2gl/__init__.py
gh2gl/auth.py
gh2gl/cli.py
gh2gl/mirror.py
gh2gl-0.1.0.dist-info/LICENSE
gh2gl-0.1.0.dist-info/METADATA
gh2gl-0.1.0.dist-info/WHEEL
gh2gl-0.1.0.dist-info/entry_points.txt
gh2gl-0.1.0.dist-info/RECORD
