Metadata-Version: 2.3
Name: gh2gl
Version: 0.1.0
Summary: 
License: MIT
Author: viniciusccosta
Author-email: viniciusccosta95@gmail.com
Requires-Python: >=3.13,<4.0
Classifier: License :: OSI Approved :: MIT License
Classifier: Programming Language :: Python :: 3
Classifier: Programming Language :: Python :: 3.13
Requires-Dist: keyring (>=25.6.0,<26.0.0)
Requires-Dist: python-decouple (>=3.8,<4.0)
Requires-Dist: requests (>=2.32.5,<3.0.0)
Requires-Dist: rich (>=13.7.0,<14.0.0)
Requires-Dist: typer (>=0.19.2,<0.20.0)
